metapredictor/__init__.py
metapredictor/evaluation/__init__.py
tests/__init__.py
tests/utils.py
tests/evaluation/__init__.py
Metapredictor-0.0.0.dist-info/LICENSE
Metapredictor-0.0.0.dist-info/METADATA
Metapredictor-0.0.0.dist-info/WHEEL
Metapredictor-0.0.0.dist-info/top_level.txt
Metapredictor-0.0.0.dist-info/RECORD
