Metadata-Version: 2.1
Name: Metapredictor
Version: 0.0.0
Summary: A Human-Centered Evaluation Framework for Explainability Methods
Author: Thomas FEL, Julien Colin
Author-email: thomas_fel@brown.edu
License: MIT
Classifier: Development Status :: 4 - Beta
Classifier: License :: OSI Approved :: MIT License
Classifier: Programming Language :: Python
Classifier: Programming Language :: Python :: 3
Classifier: Operating System :: OS Independent
Requires-Python: >=3.6
License-File: LICENSE
Requires-Dist: tensorflow
Requires-Dist: pytorch
Requires-Dist: xplique
Requires-Dist: numpy
Requires-Dist: scikit-image
Requires-Dist: matplotlib
Requires-Dist: scipy
Requires-Dist: opencv-python
Provides-Extra: docs
Requires-Dist: mkdocs ; extra == 'docs'
Requires-Dist: mkdocs-material ; extra == 'docs'
Requires-Dist: numkdoc ; extra == 'docs'
Provides-Extra: tests
Requires-Dist: pytest ; extra == 'tests'
Requires-Dist: pylint ; extra == 'tests'
